{
  "errors": {
    "cdc": "missing CDC fast facts"
  },
  "generated_at": "2026-07-23T16:48:43Z",
  "schema_version": 2,
  "sources": {
    "cdc": {
      "cases": 1645,
      "deaths": 0,
      "fetched_at": "2026-07-21T16:45:11Z",
      "hospitalizations": 141,
      "official_as_of": "2026-07-13",
      "source_url": "https://www.cdc.gov/cyclosporiasis/php/surveillance/index.html",
      "states": 34,
      "validation_status": "last-known-good"
    },
    "fda": {
      "fetched_at": "2026-07-23T16:48:43Z",
      "investigations": [
        {
          "cases": 72,
          "date_posted": "2026-07-22",
          "reference": "1392",
          "status": "ongoing"
        },
        {
          "cases": null,
          "date_posted": "2026-07-15",
          "reference": "1390",
          "status": "active"
        },
        {
          "cases": 10,
          "date_posted": "2026-07-08",
          "reference": "1385",
          "status": "ongoing"
        },
        {
          "cases": 18,
          "date_posted": "2026-07-08",
          "reference": "1384",
          "status": "ongoing"
        },
        {
          "cases": 2,
          "date_posted": "2026-06-17",
          "reference": "1381",
          "status": "ended"
        },
        {
          "cases": 8,
          "date_posted": "2026-06-03",
          "reference": "1375",
          "status": "ended"
        }
      ],
      "official_as_of": "2026-07-22",
      "source_url": "https://www.fda.gov/food/outbreaks-foodborne-illness/investigations-foodborne-illness-outbreaks",
      "validation_status": "valid"
    },
    "mdhhs": {
      "cases": 7664,
      "fetched_at": "2026-07-23T16:48:43Z",
      "hospitalizations": 160,
      "official_as_of": "2026-07-23",
      "source_url": "https://www.michigan.gov/mdhhs/keep-mi-healthy/infectious-diseases/infectious-disease-outbreaks",
      "validation_status": "valid"
    },
    "nndss": {
      "fetched_at": "2026-07-23T16:48:43Z",
      "jurisdictions": {
        "AK": {
          "cases": 6
        },
        "AL": {
          "cases": 25
        },
        "AR": {
          "cases": 24
        },
        "AZ": {
          "cases": 24
        },
        "CA": {
          "cases": 143
        },
        "CO": {
          "cases": 189
        },
        "CT": {
          "cases": 44
        },
        "DC": {
          "cases": 0
        },
        "DE": {
          "cases": 0
        },
        "FL": {
          "cases": 168
        },
        "GA": {
          "cases": 100
        },
        "HI": {
          "cases": 0
        },
        "IA": {
          "cases": 1
        },
        "ID": {
          "status": "not-reportable"
        },
        "IL": {
          "cases": 94
        },
        "IN": {
          "cases": 34
        },
        "KS": {
          "cases": 250
        },
        "KY": {
          "cases": 169
        },
        "LA": {
          "cases": 62
        },
        "MA": {
          "cases": 69
        },
        "MD": {
          "cases": 81
        },
        "ME": {
          "cases": 2
        },
        "MI": {
          "cases": 3380
        },
        "MN": {
          "cases": 0
        },
        "MO": {
          "cases": 0
        },
        "MS": {
          "status": "not-reportable"
        },
        "MT": {
          "cases": 0
        },
        "NC": {
          "cases": 80
        },
        "ND": {
          "cases": 5
        },
        "NE": {
          "cases": 65
        },
        "NH": {
          "cases": 5
        },
        "NJ": {
          "cases": 103
        },
        "NM": {
          "cases": 5
        },
        "NV": {
          "cases": 5
        },
        "NY": {
          "cases": 642,
          "components": {
            "nyc": 484,
            "state_excluding_nyc": 158
          }
        },
        "OH": {
          "cases": 1667
        },
        "OK": {
          "cases": 116
        },
        "OR": {
          "cases": 20
        },
        "PA": {
          "status": "not-reportable"
        },
        "RI": {
          "cases": 9
        },
        "SC": {
          "cases": 20
        },
        "SD": {
          "cases": 0
        },
        "TN": {
          "cases": 66
        },
        "TX": {
          "cases": 9
        },
        "UT": {
          "cases": 23
        },
        "VA": {
          "cases": 85
        },
        "VT": {
          "cases": 0
        },
        "WA": {
          "cases": 0
        },
        "WI": {
          "cases": 95
        },
        "WV": {
          "cases": 22
        },
        "WY": {
          "cases": 0
        }
      },
      "official_as_of": "2026-07-18",
      "reporting_period": "cumulative YTD 2026",
      "source_url": "https://data.cdc.gov/resource/x9gk-5huc.json?$where=year%3D%272026%27%20and%20label%3D%27Cyclosporiasis%27&$limit=5000",
      "us_residents_total": 7907,
      "validation_status": "valid"
    }
  },
  "state_data": {
    "AK": {
      "cases": 6,
      "comparable_cases": 6,
      "official_as_of": "2026-07-18",
      "source": "CDC NNDSS"
    },
    "AL": {
      "cases": 25,
      "comparable_cases": 25,
      "official_as_of": "2026-07-18",
      "source": "CDC NNDSS"
    },
    "AR": {
      "cases": 24,
      "comparable_cases": 24,
      "official_as_of": "2026-07-18",
      "source": "CDC NNDSS"
    },
    "AZ": {
      "cases": 24,
      "comparable_cases": 24,
      "official_as_of": "2026-07-18",
      "source": "CDC NNDSS"
    },
    "CA": {
      "cases": 143,
      "comparable_cases": 143,
      "official_as_of": "2026-07-18",
      "source": "CDC NNDSS"
    },
    "CO": {
      "cases": 189,
      "comparable_cases": 189,
      "official_as_of": "2026-07-18",
      "source": "CDC NNDSS"
    },
    "CT": {
      "cases": 44,
      "comparable_cases": 44,
      "official_as_of": "2026-07-18",
      "source": "CDC NNDSS"
    },
    "DC": {
      "cases": 0,
      "comparable_cases": 0,
      "official_as_of": "2026-07-18",
      "source": "CDC NNDSS"
    },
    "DE": {
      "cases": 0,
      "comparable_cases": 0,
      "official_as_of": "2026-07-18",
      "source": "CDC NNDSS"
    },
    "FL": {
      "cases": 168,
      "comparable_cases": 168,
      "official_as_of": "2026-07-18",
      "source": "CDC NNDSS"
    },
    "GA": {
      "cases": 100,
      "comparable_cases": 100,
      "official_as_of": "2026-07-18",
      "source": "CDC NNDSS"
    },
    "HI": {
      "cases": 0,
      "comparable_cases": 0,
      "official_as_of": "2026-07-18",
      "source": "CDC NNDSS"
    },
    "IA": {
      "cases": 1,
      "comparable_cases": 1,
      "official_as_of": "2026-07-18",
      "source": "CDC NNDSS"
    },
    "IL": {
      "cases": 94,
      "comparable_cases": 94,
      "official_as_of": "2026-07-18",
      "source": "CDC NNDSS"
    },
    "IN": {
      "cases": 34,
      "comparable_cases": 34,
      "official_as_of": "2026-07-18",
      "source": "CDC NNDSS"
    },
    "KS": {
      "cases": 250,
      "comparable_cases": 250,
      "official_as_of": "2026-07-18",
      "source": "CDC NNDSS"
    },
    "KY": {
      "cases": 169,
      "comparable_cases": 169,
      "official_as_of": "2026-07-18",
      "source": "CDC NNDSS"
    },
    "LA": {
      "cases": 62,
      "comparable_cases": 62,
      "official_as_of": "2026-07-18",
      "source": "CDC NNDSS"
    },
    "MA": {
      "cases": 69,
      "comparable_cases": 69,
      "official_as_of": "2026-07-18",
      "source": "CDC NNDSS"
    },
    "MD": {
      "cases": 81,
      "comparable_cases": 81,
      "official_as_of": "2026-07-18",
      "source": "CDC NNDSS"
    },
    "ME": {
      "cases": 2,
      "comparable_cases": 2,
      "official_as_of": "2026-07-18",
      "source": "CDC NNDSS"
    },
    "MI": {
      "cases": 7664,
      "comparable_cases": 3380,
      "official_as_of": "2026-07-23",
      "scope": "state outbreak reports; may include probable and confirmed cases",
      "source": "Michigan MDHHS"
    },
    "MN": {
      "cases": 0,
      "comparable_cases": 0,
      "official_as_of": "2026-07-18",
      "source": "CDC NNDSS"
    },
    "MO": {
      "cases": 0,
      "comparable_cases": 0,
      "official_as_of": "2026-07-18",
      "source": "CDC NNDSS"
    },
    "MT": {
      "cases": 0,
      "comparable_cases": 0,
      "official_as_of": "2026-07-18",
      "source": "CDC NNDSS"
    },
    "NC": {
      "cases": 80,
      "comparable_cases": 80,
      "official_as_of": "2026-07-18",
      "source": "CDC NNDSS"
    },
    "ND": {
      "cases": 5,
      "comparable_cases": 5,
      "official_as_of": "2026-07-18",
      "source": "CDC NNDSS"
    },
    "NE": {
      "cases": 65,
      "comparable_cases": 65,
      "official_as_of": "2026-07-18",
      "source": "CDC NNDSS"
    },
    "NH": {
      "cases": 5,
      "comparable_cases": 5,
      "official_as_of": "2026-07-18",
      "source": "CDC NNDSS"
    },
    "NJ": {
      "cases": 103,
      "comparable_cases": 103,
      "official_as_of": "2026-07-18",
      "source": "CDC NNDSS"
    },
    "NM": {
      "cases": 5,
      "comparable_cases": 5,
      "official_as_of": "2026-07-18",
      "source": "CDC NNDSS"
    },
    "NV": {
      "cases": 5,
      "comparable_cases": 5,
      "official_as_of": "2026-07-18",
      "source": "CDC NNDSS"
    },
    "NY": {
      "cases": 642,
      "comparable_cases": 642,
      "components": {
        "nyc": 484,
        "state_excluding_nyc": 158
      },
      "official_as_of": "2026-07-18",
      "source": "CDC NNDSS"
    },
    "OH": {
      "cases": 1667,
      "comparable_cases": 1667,
      "official_as_of": "2026-07-18",
      "source": "CDC NNDSS"
    },
    "OK": {
      "cases": 116,
      "comparable_cases": 116,
      "official_as_of": "2026-07-18",
      "source": "CDC NNDSS"
    },
    "OR": {
      "cases": 20,
      "comparable_cases": 20,
      "official_as_of": "2026-07-18",
      "source": "CDC NNDSS"
    },
    "RI": {
      "cases": 9,
      "comparable_cases": 9,
      "official_as_of": "2026-07-18",
      "source": "CDC NNDSS"
    },
    "SC": {
      "cases": 20,
      "comparable_cases": 20,
      "official_as_of": "2026-07-18",
      "source": "CDC NNDSS"
    },
    "SD": {
      "cases": 0,
      "comparable_cases": 0,
      "official_as_of": "2026-07-18",
      "source": "CDC NNDSS"
    },
    "TN": {
      "cases": 66,
      "comparable_cases": 66,
      "official_as_of": "2026-07-18",
      "source": "CDC NNDSS"
    },
    "TX": {
      "cases": 9,
      "comparable_cases": 9,
      "official_as_of": "2026-07-18",
      "source": "CDC NNDSS"
    },
    "UT": {
      "cases": 23,
      "comparable_cases": 23,
      "official_as_of": "2026-07-18",
      "source": "CDC NNDSS"
    },
    "VA": {
      "cases": 85,
      "comparable_cases": 85,
      "official_as_of": "2026-07-18",
      "source": "CDC NNDSS"
    },
    "VT": {
      "cases": 0,
      "comparable_cases": 0,
      "official_as_of": "2026-07-18",
      "source": "CDC NNDSS"
    },
    "WA": {
      "cases": 0,
      "comparable_cases": 0,
      "official_as_of": "2026-07-18",
      "source": "CDC NNDSS"
    },
    "WI": {
      "cases": 95,
      "comparable_cases": 95,
      "official_as_of": "2026-07-18",
      "source": "CDC NNDSS"
    },
    "WV": {
      "cases": 22,
      "comparable_cases": 22,
      "official_as_of": "2026-07-18",
      "source": "CDC NNDSS"
    },
    "WY": {
      "cases": 0,
      "comparable_cases": 0,
      "official_as_of": "2026-07-18",
      "source": "CDC NNDSS"
    }
  }
}
